batch_table_service/__init__.py
batch_table_service/_batch_table.py
batch_table_service/_table_service.py
batch_table_storage-0.0.9.dist-info/LICENCE
batch_table_storage-0.0.9.dist-info/METADATA
batch_table_storage-0.0.9.dist-info/WHEEL
batch_table_storage-0.0.9.dist-info/top_level.txt
batch_table_storage-0.0.9.dist-info/RECORD
